bonadmin/__init__.py
bonadmin/cli.py
bonadmin/example_config.yaml
bonadmin-1.1.1.dist-info/METADATA
bonadmin-1.1.1.dist-info/WHEEL
bonadmin-1.1.1.dist-info/entry_points.txt
bonadmin-1.1.1.dist-info/top_level.txt
bonadmin-1.1.1.dist-info/RECORD
