Metadata-Version: 2.4
Name: bonadmin
Version: 1.1.1
Summary: CLI Tools for Bot or Not sessions management
Requires-Python: >=3.9
Requires-Dist: typer>=0.12.3
Requires-Dist: PyYAML>=6.0.1
Requires-Dist: requests>=2.31.0
